turkcepython/__init__.py
turkcepython/cli.py
turkcepython-0.1.1.dist-info/LICENSE.txt
turkcepython-0.1.1.dist-info/METADATA
turkcepython-0.1.1.dist-info/WHEEL
turkcepython-0.1.1.dist-info/top_level.txt
turkcepython-0.1.1.dist-info/RECORD
