Metadata-Version: 2.1
Name: turkcepython
Version: 0.1.1
Summary: Türkçe anahtar kelimelerle Python yazmayı sağlayan eğitim amaçlı bir paket.
Author: Utku Coban
License: MIT
Classifier: Programming Language :: Python :: 3
Classifier: License :: OSI Approved :: MIT License
Classifier: Natural Language :: Turkish
Classifier: Intended Audience :: Education
License-File: LICENSE.txt
